odoo9_addon_account_invoice_fixed_discount-9.0.1.0.0-py2.7-nspkg.pth
odoo9_addon_account_invoice_fixed_discount-9.0.1.0.0.dist-info/DESCRIPTION.rst
odoo9_addon_account_invoice_fixed_discount-9.0.1.0.0.dist-info/METADATA
odoo9_addon_account_invoice_fixed_discount-9.0.1.0.0.dist-info/RECORD
odoo9_addon_account_invoice_fixed_discount-9.0.1.0.0.dist-info/WHEEL
odoo9_addon_account_invoice_fixed_discount-9.0.1.0.0.dist-info/metadata.json
odoo9_addon_account_invoice_fixed_discount-9.0.1.0.0.dist-info/namespace_packages.txt
odoo9_addon_account_invoice_fixed_discount-9.0.1.0.0.dist-info/top_level.txt
odoo_addons/account_invoice_fixed_discount/README.rst
odoo_addons/account_invoice_fixed_discount/__init__.py
odoo_addons/account_invoice_fixed_discount/__openerp__.py
odoo_addons/account_invoice_fixed_discount/models/__init__.py
odoo_addons/account_invoice_fixed_discount/models/account_invoice.py
odoo_addons/account_invoice_fixed_discount/reports/report_account_invoice.xml
odoo_addons/account_invoice_fixed_discount/static/description/icon.png
odoo_addons/account_invoice_fixed_discount/tests/__init__.py
odoo_addons/account_invoice_fixed_discount/tests/test_account_fixed_discount.py
odoo_addons/account_invoice_fixed_discount/views/account_invoice_view.xml
